aqimon/__init__.py
aqimon/aqi_common.py
aqimon/config.py
aqimon/database.py
aqimon/read/__init__.py
aqimon/read/mock.py
aqimon/read/novapm.py
aqimon/server.py
aqimon/static/android-chrome-192x192.png
aqimon/static/android-chrome-512x512.png
aqimon/static/apple-touch-icon.png
aqimon/static/elm.js
aqimon/static/favicon-16x16.png
aqimon/static/favicon-32x32.png
aqimon/static/favicon.ico
aqimon/static/images/aqimon.png
aqimon/static/images/failing.png
aqimon/static/images/idle.png
aqimon/static/images/loading.gif
aqimon/static/images/warmingup.gif
aqimon/static/index.html
aqimon-0.6.0.dist-info/LICENSE
aqimon-0.6.0.dist-info/METADATA
aqimon-0.6.0.dist-info/WHEEL
aqimon-0.6.0.dist-info/entry_points.txt
aqimon-0.6.0.dist-info/RECORD
